README.md
setup.py
babex.egg-info/PKG-INFO
babex.egg-info/SOURCES.txt
babex.egg-info/dependency_links.txt
babex.egg-info/requires.txt
babex.egg-info/top_level.txt
src/Message.py
src/Path.py
src/Service.py
src/__init__.py
src/errors.py