Metadata-Version: 1.2
Name: babex
Version: 1.0.6
Summary: Babex is a modern solution for communications between microservices.
Home-page: https://github.com/spyzhov/babex-py
Author: Stepan Pyzhov
Author-email: turin.tomsk@gmail.com
Maintainer: Stepan Pyzhov
License: UNKNOWN
Platform: UNKNOWN
